vvv_tools/__init__.py
vvv_tools/Packages/v_terminux.py
vvv_tools/Packages/User/Default (Windows).sublime-keymap
vvv_tools/Packages/User/Preferences.sublime-settings
vvv_tools/Packages/User/c_tcc.sublime-build
vvv_tools/Packages/User/cmdline.sublime-build
vvv_tools/Packages/User/nodejs.sublime-build
vvv_tools/Packages/User/v_snippet/tcc_dll.sublime-snippet
vvv_tools/Packages/User/v_snippet/tcc_dll_inject.sublime-snippet
vvv_tools/Packages/User/v_snippet/tcc_dll_inject_wechat.sublime-snippet
vvv_tools/Packages/User/v_snippet/tcc_dll_inject_wechat2.sublime-snippet
vvv_tools/Packages/User/v_snippet/tcc_dll_inject_win.sublime-snippet
vvv_tools/Packages/User/v_snippet/tcc_dll_make_bit.sublime-snippet
vvv_tools/Packages/User/v_snippet/tcc_hack_l4d2.sublime-snippet
vvv_tools/Packages/User/v_snippet/tcc_minhook.sublime-snippet
vvv_tools/Packages/User/v_snippet/tcc_syswhispers2.sublime-snippet
vvv_tools/Packages/User/v_snippet/tcc_tool_funcs.sublime-snippet
vvv_tools/Packages/User/v_snippet/tcc_win.sublime-snippet
vvv_tools/yolo/README.txt
vvv_tools/yolo/cnn_predict.py
vvv_tools/yolo/cnn_train.py
vvv_tools/yolo/cnn_v2_predict.py
vvv_tools/yolo/cnn_v2_train.py
vvv_tools/yolo/siam_predict.py
vvv_tools/yolo/siam_train.py
vvv_tools/yolo/yolo_predict.py
vvv_tools/yolo/yolo_train.py
vvv_tools/yolo/__onnx/__make_onnx.py
vvv_tools/yolo/__onnx/__make_onnx_new.py
vvv_tools/yolo/__onnx/__make_onnx_siam.py
vvv_tools/yolo/imgs/__1图像预处理_裁剪二值化之类的.py
vvv_tools/yolo/imgs/__2小量数据训练后_预标注.py
vvv_tools/yolo/imgs/__3将yolo中的图片切出来并分好类.py
vvv_tools/yolo/imgs/__4分类图片扩展补充.py
vvv_tools/yolo/imgs/__5原始图片劣质化处理补充.py
vvv_tools/yolo/imgs/data/README.txt
vvv_tools/yolo/ml/cnn.py
vvv_tools/yolo/ml/cnn_v2.py
vvv_tools/yolo/ml/siam.py
vvv_tools/yolo/ml/yolo.py
vvv_tools/yolo/mods/README.txt
vvv_tools-0.4.0.dist-info/METADATA
vvv_tools-0.4.0.dist-info/WHEEL
vvv_tools-0.4.0.dist-info/entry_points.txt
vvv_tools-0.4.0.dist-info/top_level.txt
vvv_tools-0.4.0.dist-info/RECORD
