Metadata-Version: 2.1
Name: vvv-tools
Version: 0.4.0
Requires-Dist: vvv-tools-stable>=0.0.4
